llama_stack_provider_ragas/__init__.py
llama_stack_provider_ragas/compat.py
llama_stack_provider_ragas/config.py
llama_stack_provider_ragas/constants.py
llama_stack_provider_ragas/errors.py
llama_stack_provider_ragas/logging_utils.py
llama_stack_provider_ragas/provider.py
llama_stack_provider_ragas/inline/__init__.py
llama_stack_provider_ragas/inline/provider.py
llama_stack_provider_ragas/inline/ragas_inline_eval.py
llama_stack_provider_ragas/inline/wrappers_inline.py
llama_stack_provider_ragas/remote/__init__.py
llama_stack_provider_ragas/remote/provider.py
llama_stack_provider_ragas/remote/ragas_remote_eval.py
llama_stack_provider_ragas/remote/wrappers_remote.py
llama_stack_provider_ragas/remote/kubeflow/__init__.py
llama_stack_provider_ragas/remote/kubeflow/components.py
llama_stack_provider_ragas/remote/kubeflow/pipeline.py
llama_stack_provider_ragas/remote/kubeflow/utils.py
llama_stack_provider_ragas-0.5.2.dist-info/METADATA
llama_stack_provider_ragas-0.5.2.dist-info/WHEEL
llama_stack_provider_ragas-0.5.2.dist-info/licenses/LICENCE
llama_stack_provider_ragas-0.5.2.dist-info/RECORD
