Metadata-Version: 2.4
Name: llama-stack-provider-ragas
Version: 0.5.2
Summary: Ragas evaluation as an out-of-tree Llama Stack provider
Project-URL: homepage, https://github.com/trustyai-explainability/llama-stack-provider-ragas
Project-URL: repository, https://github.com/trustyai-explainability/llama-stack-provider-ragas
Author: Trusty AI Team
Author-email: Diego Maniloff <dmanilof@redhat.com>
License-Expression: Apache-2.0
License-File: LICENCE
Keywords: evaluation,llama-stack,ragas
Classifier: Intended Audience :: Developers
Classifier: Intended Audience :: Information Technology
Classifier: Intended Audience :: Science/Research
Classifier: License :: OSI Approved :: Apache Software License
Classifier: Operating System :: OS Independent
Classifier: Programming Language :: Python :: 3
Requires-Python: >=3.12
Requires-Dist: datasets>=2.16.0
Requires-Dist: greenlet==3.2.4
Requires-Dist: llama-stack-client>=0.4.0
Requires-Dist: llama-stack>=0.4.0
Requires-Dist: pandas<2.3.0
Requires-Dist: pyarrow>=21.0.0
Requires-Dist: ragas==0.3.0
Requires-Dist: requests>=2.32.5
Requires-Dist: setuptools-scm
Provides-Extra: dev
Requires-Dist: aiosqlite; extra == 'dev'
Requires-Dist: ipykernel; extra == 'dev'
Requires-Dist: kfp-kubernetes>=2.0.0; extra == 'dev'
Requires-Dist: kfp-pipeline-spec>=2.0.0; extra == 'dev'
Requires-Dist: kfp-server-api>=2.0.0; extra == 'dev'
Requires-Dist: kfp>=2.5.0; extra == 'dev'
Requires-Dist: kubernetes>=30.0.0; extra == 'dev'
Requires-Dist: mypy; extra == 'dev'
Requires-Dist: ollama; extra == 'dev'
Requires-Dist: opentelemetry-api; extra == 'dev'
Requires-Dist: opentelemetry-exporter-otlp; extra == 'dev'
Requires-Dist: pre-commit; extra == 'dev'
Requires-Dist: pytest; extra == 'dev'
Requires-Dist: pytest-asyncio; extra == 'dev'
Requires-Dist: pytest-cov; extra == 'dev'
Requires-Dist: rich; extra == 'dev'
Requires-Dist: ruff; extra == 'dev'
Requires-Dist: s3fs>=2024.12.0; extra == 'dev'
Requires-Dist: uvicorn; extra == 'dev'
Provides-Extra: distro
Requires-Dist: aiosqlite; extra == 'distro'
Requires-Dist: ollama; extra == 'distro'
Requires-Dist: opentelemetry-api; extra == 'distro'
Requires-Dist: opentelemetry-exporter-otlp; extra == 'distro'
Requires-Dist: uvicorn; extra == 'distro'
Provides-Extra: remote
Requires-Dist: kfp-kubernetes>=2.0.0; extra == 'remote'
Requires-Dist: kfp-pipeline-spec>=2.0.0; extra == 'remote'
Requires-Dist: kfp-server-api>=2.0.0; extra == 'remote'
Requires-Dist: kfp>=2.5.0; extra == 'remote'
Requires-Dist: kubernetes>=30.0.0; extra == 'remote'
Requires-Dist: s3fs>=2024.12.0; extra == 'remote'
